Pika_Pokemon_Library/__init__.py
Pika_Pokemon_Library/pokemon.csv
Pika_Pokemon_Library/random_pokemon.py
Pika_Pokemon_Library-1.0.1.dist-info/METADATA
Pika_Pokemon_Library-1.0.1.dist-info/WHEEL
Pika_Pokemon_Library-1.0.1.dist-info/top_level.txt
Pika_Pokemon_Library-1.0.1.dist-info/RECORD
